geometry/__init__.py
geometry/canvas.py
geometry/group.py
geometry/handles.py
geometry/mixins.py
geometry/path.py
geometry/point.py
geometry/py.typed
geometry/rect.py
geometry/translate.py
geometry/userdata.py
geometry/version.py
simple_geometry-0.1.4.dist-info/LICENSE
simple_geometry-0.1.4.dist-info/METADATA
simple_geometry-0.1.4.dist-info/WHEEL
simple_geometry-0.1.4.dist-info/top_level.txt
simple_geometry-0.1.4.dist-info/RECORD
