Metadata-Version: 2.1
Name: simple-geometry
Version: 0.1.4
Summary: A simple geometry library
Home-page: UNKNOWN
Author: Niels Buwen
Author-email: dev@niels-buwen.de
License: UNKNOWN
Platform: UNKNOWN
Classifier: Development Status :: 4 - Beta
Classifier: Programming Language :: Python :: 3
Classifier: Programming Language :: Python :: 3.6
Classifier: Programming Language :: Python :: 3.7
Classifier: Programming Language :: Python :: 3.8
Classifier: Intended Audience :: Developers
Classifier: Operating System :: POSIX :: Linux
Classifier: Topic :: Software Development
Classifier: License :: OSI Approved :: GNU Lesser General Public License v3 (LGPLv3)
Requires-Dist: dataclasses ; python_version < "3.7"
